commands/__init__.py
commands/_all_tests.py
commands/run.py
commands/send.py
commands/shell.py
commands/tasks.py
commands/test.py
testapp/__init__.py
testapp/controllers/__init__.py
testapp/controllers/auth_controller.py
testapp/controllers/main.py
testapp/models/__init__.py
testapp/models/token.py
testapp/models/user.py
testapp/tests/__init__.py
uengine/__init__.py
uengine/__main__.py
uengine/afterlife.py
uengine/api.py
uengine/base.py
uengine/cache.py
uengine/client.py
uengine/context.py
uengine/db.py
uengine/errors.py
uengine/file_cache.py
uengine/json_encoder.py
uengine/profilers.py
uengine/queue.py
uengine/requirements.txt
uengine/sessions.py
uengine/utils.py
uengine/controllers/__init__.py
uengine/models/__init__.py
uengine/models/abstract_model.py
uengine/models/model_hook.py
uengine/models/sharded_model.py
uengine/models/storable_model.py
uengine/models/submodel.py
uengine/project_source_templates/micro.py
uengine/project_source_templates/requirements.txt
uengine/project_source_templates/wsgi.py
uengine/project_source_templates/__appdir__/__init__.py
uengine/project_source_templates/__appdir__/requirements.txt
uengine/project_source_templates/__appdir__/controllers/__init__.py
uengine/project_source_templates/__appdir__/controllers/auth_controller.py
uengine/project_source_templates/__appdir__/controllers/main.py
uengine/project_source_templates/__appdir__/models/__init__.py
uengine/project_source_templates/__appdir__/models/token.py
uengine/project_source_templates/__appdir__/models/user.py
uengine/project_source_templates/__appdir__/tests/__init__.py
uengine/project_source_templates/commands/__init__.py
uengine/project_source_templates/commands/__init__.pyc
uengine/project_source_templates/commands/_all_tests.py
uengine/project_source_templates/commands/index.py
uengine/project_source_templates/commands/index.pyc
uengine/project_source_templates/commands/lint.py
uengine/project_source_templates/commands/run.py
uengine-3.6.13.dist-info/METADATA
uengine-3.6.13.dist-info/WHEEL
uengine-3.6.13.dist-info/entry_points.txt
uengine-3.6.13.dist-info/top_level.txt
uengine-3.6.13.dist-info/RECORD
